{"type": "Feature", "id": 12514621, "properties": {"woe:id": 12514621, "woe:parent_id": 821609, "woe:name": "Plavec Airport", "woe:placetype": 14, "woe:placetype_name": "Airport", "woe:lang": "ENG", "iso:country": "SK", "meta:provider": ["geoplanet:7.3.1", "geoplanet:7.3.2", "geoplanet:7.4.0", "geoplanet:7.4.1", "geoplanet:7.5.1", "geoplanet:7.5.2", "geoplanet:7.6.0", "geoplanet:7.8.1", "geoplanet:7.9.0", "geoplanet:7.10.0", "geoplanet:8.0.0", "woeplanet:8.0.0"], "meta:indexed": "2020-08-20T20:49:12.756124", "meta:updated": "2020-08-22T02:46:47.657583", "woe:hierarchy": {"continent": 24865675, "country": 23424877, "town": 0, "planet": 1, "county": 29399296, "suburb": 0, "state": 20070496, "region": 0, "localadmin": 29399570}, "woe:timezone_id": 28350912, "woe:hash": "u2yb6150sswe", "woe:centroid": [20.8344, 49.268299], "geom:latitude": 49.268299, "geom:longitude": 20.8344, "geom:hash": "u2yb6150sswe", "woe:latitude": 49.268299, "geom:centroid": [20.8344, 49.268299], "woe:longitude": 20.8344, "woe:repo": "woeplanet-airport-sk"}, "geometry": {"coordinates": [20.8344, 49.268299], "type": "Point"}}