{"type": "Feature", "id": 12514609, "geometry": {"type": "Point", "coordinates": [18.2043, 48.9972]}, "properties": {"woe:id": 12514609, "woe:parent_id": 819912, "woe:name": "Dubnica Nad Vahom Airport", "woe:placetype": 14, "woe:placetype_name": "Airport", "woe:lang": "ENG", "iso:country": "SK", "meta:provider": ["geoplanet:7.3.1", "geoplanet:7.3.2", "geoplanet:7.4.0", "geoplanet:7.4.1", "geoplanet:7.5.1", "geoplanet:7.5.2", "geoplanet:7.6.0", "geoplanet:7.8.1", "geoplanet:7.9.0", "geoplanet:7.10.0", "geoplanet:8.0.0", "woeplanet:8.0.0"], "meta:indexed": "2020-08-20T20:49:12.749690", "meta:updated": "2020-10-14T11:22:56.291086", "woe:hierarchy": {"continent": 24865675, "country": 23424877, "town": 0, "planet": 1, "county": 29399312, "suburb": 0, "state": 20070493, "region": 0, "localadmin": 29400236}, "woe:timezone_id": 28350912, "woe:hash": "u2sywpxvqujf", "woe:centroid": [18.2043, 48.9972], "geom:latitude": 48.9972, "geom:longitude": 18.2043, "geom:hash": "u2sywpxvqujf", "woe:latitude": 48.9972, "geom:centroid": [18.2043, 48.9972], "woe:longitude": 18.2043, "woe:repo": "woeplanet-airport-sk", "geom:area": 0.0, "woe:scale": 19}}